techathonai/__init__.py
techathonai-1.0.1.dist-info/LICENCE.md
techathonai-1.0.1.dist-info/METADATA
techathonai-1.0.1.dist-info/WHEEL
techathonai-1.0.1.dist-info/top_level.txt
techathonai-1.0.1.dist-info/RECORD
